{
  "_class": "shapePath",
  "booleanOperation": 0,
  "do_objectID": "2ED7B7E0-FB01-43EA-A4E3-CD0FDC2D8764",
  "edited": true,
  "exportOptions": {
    "_class": "exportOptions",
    "exportFormats": [
    ],
    "includedLayerIds": [
    ],
    "layerOptions": 0,
    "shouldTrim": false
  },
  "frame": {
    "_class": "rect",
    "constrainProportions": false,
    "height": 4.414213562373096,
    "width": 4.414213562373096,
    "x": 2.999999999999994,
    "y": 0
  },
  "isFlippedHorizontal": false,
  "isFlippedVertical": false,
  "isLocked": false,
  "isVisible": true,
  "layerListExpandedType": 0,
  "name": "Line",
  "nameIsFixed": false,
  "path": {
    "_class": "path",
    "isClosed": true,
    "pointRadiusBehaviour": 0,
    "points": [
      {
        "_class": "curvePoint",
        "cornerRadius": 0,
        "curveFrom": "{0.16018862050852042, 1}",
        "curveMode": 1,
        "curveTo": "{0.16018862050852042, 1}",
        "hasCurveFrom": false,
        "hasCurveTo": false,
        "point": "{0.16018862050852042, 1}"
      },
      {
        "_class": "curvePoint",
        "cornerRadius": 0,
        "curveFrom": "{1, 0.16018862050852031}",
        "curveMode": 1,
        "curveTo": "{1, 0.16018862050852031}",
        "hasCurveFrom": false,
        "hasCurveTo": false,
        "point": "{1, 0.16018862050852031}"
      },
      {
        "_class": "curvePoint",
        "cornerRadius": 0,
        "curveFrom": "{0.83981137949147955, 0}",
        "curveMode": 1,
        "curveTo": "{0.83981137949147955, 0}",
        "hasCurveFrom": false,
        "hasCurveTo": false,
        "point": "{0.83981137949147955, 0}"
      },
      {
        "_class": "curvePoint",
        "cornerRadius": 0,
        "curveFrom": "{0, 0.83981137949147944}",
        "curveMode": 1,
        "curveTo": "{0, 0.83981137949147944}",
        "hasCurveFrom": false,
        "hasCurveTo": false,
        "point": "{0, 0.83981137949147944}"
      }
    ]
  },
  "resizingConstraint": 63,
  "resizingType": 0,
  "rotation": 0,
  "shouldBreakMaskChain": false
}