{
  "_class": "shapePath",
  "booleanOperation": 0,
  "do_objectID": "5C63014A-9DE2-4D82-817C-499FEDAF56C2",
  "edited": true,
  "exportOptions": {
    "_class": "exportOptions",
    "exportFormats": [
    ],
    "includedLayerIds": [
    ],
    "layerOptions": 0,
    "shouldTrim": false
  },
  "frame": {
    "_class": "rect",
    "constrainProportions": false,
    "height": 9.146938775510089,
    "width": 4.502164502164443,
    "x": 7.105427357601005e-15,
    "y": 2.725046382189019
  },
  "isFlippedHorizontal": false,
  "isFlippedVertical": false,
  "isLocked": false,
  "isVisible": true,
  "layerListExpandedType": 0,
  "name": "Shape",
  "nameIsFixed": false,
  "path": {
    "_class": "path",
    "isClosed": true,
    "pointRadiusBehaviour": 0,
    "points": [
      {
        "_class": "curvePoint",
        "cornerRadius": 0,
        "curveFrom": "{0.36483516483516487, 0.70317634173055865}",
        "curveMode": 1,
        "curveTo": "{0.36483516483516487, 0.70317634173055865}",
        "hasCurveFrom": false,
        "hasCurveTo": false,
        "point": "{0.36483516483516487, 0.70317634173055865}"
      },
      {
        "_class": "curvePoint",
        "cornerRadius": 0,
        "curveFrom": "{0.36263736263736263, 1}",
        "curveMode": 1,
        "curveTo": "{0.36263736263736263, 1}",
        "hasCurveFrom": false,
        "hasCurveTo": false,
        "point": "{0.36263736263736263, 1}"
      },
      {
        "_class": "curvePoint",
        "cornerRadius": 0,
        "curveFrom": "{0, 1}",
        "curveMode": 1,
        "curveTo": "{0, 1}",
        "hasCurveFrom": false,
        "hasCurveTo": false,
        "point": "{0, 1}"
      },
      {
        "_class": "curvePoint",
        "cornerRadius": 0,
        "curveFrom": "{0, 0}",
        "curveMode": 1,
        "curveTo": "{0, 0}",
        "hasCurveFrom": false,
        "hasCurveTo": false,
        "point": "{0, 0}"
      },
      {
        "_class": "curvePoint",
        "cornerRadius": 0,
        "curveFrom": "{0.36703296703296701, 0}",
        "curveMode": 1,
        "curveTo": "{0.36703296703296701, 0}",
        "hasCurveFrom": false,
        "hasCurveTo": false,
        "point": "{0.36703296703296701, 0}"
      },
      {
        "_class": "curvePoint",
        "cornerRadius": 0,
        "curveFrom": "{0.40879120879120873, 0}",
        "curveMode": 1,
        "curveTo": "{0.40879120879120873, 0}",
        "hasCurveFrom": false,
        "hasCurveTo": false,
        "point": "{0.40879120879120873, 0}"
      },
      {
        "_class": "curvePoint",
        "cornerRadius": 0,
        "curveFrom": "{0.89010989010989006, 0}",
        "curveMode": 4,
        "curveTo": "{0.67252747252747247, 0}",
        "hasCurveFrom": true,
        "hasCurveTo": false,
        "point": "{0.67252747252747247, 0}"
      },
      {
        "_class": "curvePoint",
        "cornerRadius": 0,
        "curveFrom": "{1, 0.10405257393209202}",
        "curveMode": 4,
        "curveTo": "{0.99780219780219781, 0.035049288061336295}",
        "hasCurveFrom": false,
        "hasCurveTo": true,
        "point": "{1, 0.10405257393209202}"
      },
      {
        "_class": "curvePoint",
        "cornerRadius": 0,
        "curveFrom": "{1, 0.66046002190580533}",
        "curveMode": 4,
        "curveTo": "{1, 0.59145673603504945}",
        "hasCurveFrom": true,
        "hasCurveTo": false,
        "point": "{1, 0.59145673603504945}"
      },
      {
        "_class": "curvePoint",
        "cornerRadius": 0,
        "curveFrom": "{0.68351648351648353, 0.69550930996714144}",
        "curveMode": 4,
        "curveTo": "{0.89450549450549455, 0.69550930996714144}",
        "hasCurveFrom": false,
        "hasCurveTo": true,
        "point": "{0.68351648351648353, 0.69550930996714144}"
      },
      {
        "_class": "curvePoint",
        "cornerRadius": 0,
        "curveFrom": "{0.36483516483516487, 0.69550930996714144}",
        "curveMode": 1,
        "curveTo": "{0.36483516483516487, 0.69550930996714144}",
        "hasCurveFrom": false,
        "hasCurveTo": false,
        "point": "{0.36483516483516487, 0.69550930996714144}"
      }
    ]
  },
  "resizingConstraint": 63,
  "resizingType": 0,
  "rotation": 0,
  "shouldBreakMaskChain": false
}